celldx/__init__.py
celldx/api_requests.py
celldx/client.py
celldx/exceptions.py
celldx/utils.py
celldx/validations.py
celldx_py-1.0.2.dist-info/LICENSE
celldx_py-1.0.2.dist-info/METADATA
celldx_py-1.0.2.dist-info/WHEEL
celldx_py-1.0.2.dist-info/top_level.txt
celldx_py-1.0.2.dist-info/RECORD
