Metadata-Version: 2.1
Name: celldx-py
Version: 1.0.2
Summary: celldx-py is the Python Library to interact with the Hibou model inference API
Home-page: https://github.com/HistAI/celldx-py
Author: HistAI
Author-email: apchelnikov@hist.ai
License: UNKNOWN
Project-URL: Documentation, https://celldx.hist.ai/docs/
Platform: UNKNOWN
Classifier: Programming Language :: Python
Classifier: Programming Language :: Python :: 3.8
Classifier: Programming Language :: Python :: 3.9
Classifier: Programming Language :: Python :: 3.10
Classifier: Programming Language :: Python :: 3.11
Classifier: Programming Language :: Python :: 3.12
Classifier: License :: OSI Approved :: MIT License
Classifier: Operating System :: OS Independent
Requires-Python: >=3.8
License-File: LICENSE
Requires-Dist: requests
Requires-Dist: opencv-python
Requires-Dist: numpy
